airtoolclassifier/__init__.py
airtoolclassifier/__main__.py
airtoolclassifier/airtable_service.py
airtoolclassifier/classifier.py
airtoolclassifier/cli.py
airtoolclassifier/config.py
airtoolclassifier/openai_service.py
airtoolclassifier/prompts/role.txt
airtoolclassifier/prompts/task.txt
AIrToolClassifier-1.0.0.dist-info/LICENSE.txt
AIrToolClassifier-1.0.0.dist-info/METADATA
AIrToolClassifier-1.0.0.dist-info/WHEEL
AIrToolClassifier-1.0.0.dist-info/entry_points.txt
AIrToolClassifier-1.0.0.dist-info/top_level.txt
AIrToolClassifier-1.0.0.dist-info/RECORD
