Metadata-Version: 2.1
Name: AIrToolClassifier
Version: 1.0.0
Summary: Automate digital tool categorization and uncover potential use-cases with AIrToolClassifier.
Home-page: https://github.com/christophbeckmann/AIrToolClassifier
Author: Christoph Beckmann
Author-email: contact@christophbeckmann.de
License: MIT
Project-URL: Source, https://github.com/Christoph-Beckmann/AIrToolClassifier
Project-URL: Tracker, https://github.com/Christoph-Beckmann/AIrToolClassifier/issues
Platform: any
Classifier: Development Status :: 4 - Beta
Classifier: Programming Language :: Python :: 3.12
License-File: LICENSE.txt
Requires-Dist: importlib-metadata
Requires-Dist: python-dotenv ==1.0.1
Requires-Dist: prompt-toolkit >=3.0.43
Requires-Dist: validators >=0.22.0
Requires-Dist: openai >=1.12.0
Requires-Dist: pyairtable >=2.2.2
Provides-Extra: testing
Requires-Dist: setuptools ; extra == 'testing'
Requires-Dist: wheel ; extra == 'testing'
Requires-Dist: pytest ; extra == 'testing'
Requires-Dist: twine ; extra == 'testing'
